<?xml version="1.0" encoding="utf-8"?>
<!-- Created by ModBuddy on 2/14/2016 7:15:29 PM -->
<GameData>
	<Policy_GreatWorkYieldChanges>
		<Update>
			<Set Yield="4" />
			<Where PolicyType="POLICY_CREATIVE_EXPRESSION" YieldType="YIELD_CULTURE" />
		</Update>
		<Row>
			<PolicyType>POLICY_CREATIVE_EXPRESSION</PolicyType>
			<YieldType>YIELD_SCIENCE</YieldType>
			<Yield>4</Yield>
		</Row>
	</Policy_GreatWorkYieldChanges>
	<Language_en_US>
		<Delete Tag="TXT_KEY_POLICY_CREATIVE_EXPRESSION_HELP" />
		<Row Tag="TXT_KEY_POLICY_CREATIVE_EXPRESSION_HELP">
			<Text>[COLOR_POSITIVE_TEXT]Creative Expression[ENDCOLOR][NEWLINE]+4 [ICON_CULTURE] Culture and [ICON_RESEARCH] Science from each Great Work.</Text>
		</Row>
	</Language_en_US>

</GameData>